LICENSE
README.md
setup.py
bitmovin_api_sdk/__init__.py
bitmovin_api_sdk/bitmovin_api.py
bitmovin_api_sdk.egg-info/PKG-INFO
bitmovin_api_sdk.egg-info/SOURCES.txt
bitmovin_api_sdk.egg-info/dependency_links.txt
bitmovin_api_sdk.egg-info/requires.txt
bitmovin_api_sdk.egg-info/top_level.txt
bitmovin_api_sdk/account/__init__.py
bitmovin_api_sdk/account/account_api.py
bitmovin_api_sdk/account/api_keys/__init__.py
bitmovin_api_sdk/account/api_keys/api_keys_api.py
bitmovin_api_sdk/account/information/__init__.py
bitmovin_api_sdk/account/information/information_api.py
bitmovin_api_sdk/account/organizations/__init__.py
bitmovin_api_sdk/account/organizations/organizations_api.py
bitmovin_api_sdk/account/organizations/groups/__init__.py
bitmovin_api_sdk/account/organizations/groups/group_list_query_params.py
bitmovin_api_sdk/account/organizations/groups/groups_api.py
bitmovin_api_sdk/account/organizations/groups/invitations/__init__.py
bitmovin_api_sdk/account/organizations/groups/invitations/invitation_list_query_params.py
bitmovin_api_sdk/account/organizations/groups/invitations/invitations_api.py
bitmovin_api_sdk/account/organizations/groups/permissions/__init__.py
bitmovin_api_sdk/account/organizations/groups/permissions/permissions_api.py
bitmovin_api_sdk/account/organizations/groups/tenants/__init__.py
bitmovin_api_sdk/account/organizations/groups/tenants/tenant_list_query_params.py
bitmovin_api_sdk/account/organizations/groups/tenants/tenants_api.py
bitmovin_api_sdk/account/organizations/invitations/__init__.py
bitmovin_api_sdk/account/organizations/invitations/invitations_api.py
bitmovin_api_sdk/account/organizations/sub_organizations/__init__.py
bitmovin_api_sdk/account/organizations/sub_organizations/organization_list_query_params.py
bitmovin_api_sdk/account/organizations/sub_organizations/sub_organizations_api.py
bitmovin_api_sdk/account/organizations/tenants/__init__.py
bitmovin_api_sdk/account/organizations/tenants/tenants_api.py
bitmovin_api_sdk/ai_scene_analysis/__init__.py
bitmovin_api_sdk/ai_scene_analysis/ai_scene_analysis_api.py
bitmovin_api_sdk/ai_scene_analysis/analyses/__init__.py
bitmovin_api_sdk/ai_scene_analysis/analyses/analyses_api.py
