Metadata-Version: 2.1
Name: bitmovin-api-sdk
Version: 1.254.0
Summary: Python-Client which enables you to seamlessly integrate the Bitmovin API into your projects. Using this API client requires an active account.
Home-page: https://github.com/bitmovin/bitmovin-api-sdk-python
Author: Bitmovin Inc
Author-email: support@bitmovin.com
License: MIT
Keywords: Bitmovin,Bitmovin API Reference
Platform: UNKNOWN
License-File: LICENSE
